gears/__init__.py
gears/__main__.py
gears/generator.py
spec/manifest.schema.json
flywheel_gears-0.3.1.dist-info/LICENSE
flywheel_gears-0.3.1.dist-info/METADATA
flywheel_gears-0.3.1.dist-info/WHEEL
flywheel_gears-0.3.1.dist-info/top_level.txt
flywheel_gears-0.3.1.dist-info/RECORD
