Metadata-Version: 2.1
Name: flywheel-gears
Version: 0.3.1
Summary: Flywheel Gear tools
Home-page: https://gitlab.com/flywheel-io/public/gears
Author: Flywheel Exchange, LLC
Author-email: support@flywheel.io
License: UNKNOWN
Platform: UNKNOWN
License-File: LICENSE
Requires-Dist: jsonschema >=2.5.1
Requires-Dist: rfc3987 >=1.3.7
